clashaipy/__init__.py
clashaipy/chat.py
clashaipy/client.py
clashaipy/image.py
clashaipy-1.0.8.dist-info/METADATA
clashaipy-1.0.8.dist-info/WHEEL
clashaipy-1.0.8.dist-info/top_level.txt
clashaipy-1.0.8.dist-info/RECORD
