Metadata-Version: 2.1
Name: clashaipy
Version: 1.0.8
Summary: An API wrapper for the ClashAI API
Author: Julianwe17, invalidsian
License: MIT
Project-URL: GitHub, https://github.com/clashai/clashai
Project-URL: Documentation, https://clashai.readthedocs.io
Project-URL: ClashAI, https://clashai.eu
Keywords: clash-ai,clashai,api,clashapi,clashai,ai,gpt,llama,mixtral,gemini,clashaipy
Classifier: Development Status :: 4 - Beta
Classifier: License :: OSI Approved :: MIT License
Classifier: Intended Audience :: Developers
Classifier: Operating System :: OS Independent
Classifier: Programming Language :: Python :: 3.9
Classifier: Programming Language :: Python :: 3.10
Classifier: Programming Language :: Python :: 3.11
Classifier: Programming Language :: Python :: 3.12
Classifier: Programming Language :: Python :: 3.13
Requires-Python: >=3.9
Requires-Dist: requests
